{"_id":{"$oid":"5d89794081ba0d56dff18f3d"},"artist":"Jeffrey Mylett","spotifyID":"5jXWdFGg2J2qzFwnSbaonN","popularity":14.0}
{"_id":{"$oid":"5d89794081ba0d56dff18f3e"},"artist":"Dick Glasser","spotifyID":"5QlYqhKZkRj6NCgl6y0kjc","popularity":4.0}
{"_id":{"$oid":"5d89794081ba0d56dff18f3f"},"artist":"The O'Jays","spotifyID":"38h03gA85YYPeDPd9ER9rT","popularity":62.0}
{"_id":{"$oid":"5d89794081ba0d56dff18f40"},"artist":"Trippie Redd","spotifyID":"6Xgp2XMz1fhVYe7i6yNAax","popularity":86.0}
{"_id":{"$oid":"5d89794081ba0d56dff18f41"},"artist":"Blanche Thebom","spotifyID":"7qd7gnksJPMBo0uNIwkaOG","popularity":16.0}
{"_id":{"$oid":"5d89794081ba0d56dff18f42"},"artist":"Marilyn Manson","spotifyID":"2VYQTNDsvvKN9wmU5W7xpj","popularity":72.0}
{"_id":{"$oid":"5d89794081ba0d56dff18f43"},"artist":"Jeff Timmons","spotifyID":"5x0ZUfSHkTxl2zcJWtlwrR","popularity":5.0}
{"_id":{"$oid":"5d89794081ba0d56dff18f44"},"artist":"Enoch Light","spotifyID":"3bWuJAAUsvSiavkQHpOlLl","popularity":24.0}
{"_id":{"$oid":"5d89794081ba0d56dff18f45"},"artist":"John Mahon","spotifyID":"2ayhKAIwS2NYUfNW7D7dbo","popularity":0.0}
{"_id":{"$oid":"5d89794081ba0d56dff18f46"},"artist":"Boz Scaggs","spotifyID":"46njgd2Rq9tZc4ZjeQMgbh","popularity":60.0}
{"_id":{"$oid":"5d89794081ba0d56dff18f47"},"artist":"Macy Gray","spotifyID":"4ylR3zwA0zaapAu94fktwa","popularity":63.0}
{"_id":{"$oid":"5d89794081ba0d56dff18f48"},"artist":"Eddie Levert","spotifyID":"56sP86L2rYpIBMCPFlqAJD","popularity":32.0}
{"_id":{"$oid":"5d89794081ba0d56dff18f49"},"artist":"Lee Wilkof","spotifyID":"0SKowkGzEY1M8xRAJ26qfx","popularity":24.0}
{"_id":{"$oid":"5d89794081ba0d56dff18f4a"},"artist":"Joe Vitale","spotifyID":"5eqwssEcOs43l1OYA6ptnl","popularity":8.0}
{"_id":{"$oid":"5d89794081ba0d56dff18f4b"},"artist":"Troy Dillinger","spotifyID":"2csK9j6odIb0zOMXZJG1pH","popularity":0.0}
