{"_id":{"$oid":"5d897bc981ba0d56dff18fd0"},"artist":"Blac Elvis","spotifyID":"7wGEgN2eFVjvOfJh05wie9","popularity":0.0}
{"_id":{"$oid":"5d897bc981ba0d56dff18fd1"},"artist":"Johnny B. Moore","spotifyID":"1FIws8DXI9Bfv29LBhcRWX","popularity":17.0}
{"_id":{"$oid":"5d897bc981ba0d56dff18fd2"},"artist":"Rick Ross","spotifyID":"1sBkRIssrMs1AbVkOJbc7a","popularity":85.0}
{"_id":{"$oid":"5d897bc981ba0d56dff18fd3"},"artist":"Jackie Brenston","spotifyID":"2ucOV7b445I6Dl6OFN71aN","popularity":22.0}
{"_id":{"$oid":"5d897bc981ba0d56dff18fd4"},"artist":"W. C. Handy","spotifyID":"0nviSa3wK3VMjgsiNhkpd5","popularity":0.0}
{"_id":{"$oid":"5d897bc981ba0d56dff18fd5"},"artist":"Raymond Hill","spotifyID":"2oolIWne8t9nCr3P0v5v2Y","popularity":3.0}
{"_id":{"$oid":"5d897bc981ba0d56dff18fd6"},"artist":"Big Jack Johnson","spotifyID":"3tJWGXGhMM8d0r8j71wid6","popularity":14.0}
{"_id":{"$oid":"5d897bc981ba0d56dff18fd7"},"artist":"Sam Cooke","spotifyID":"6hnWRPzGGKiapVX1UCdEAC","popularity":70.0}
{"_id":{"$oid":"5d897bc981ba0d56dff18fd8"},"artist":"Louise Johnson","spotifyID":"3GZcT4xuipXe11ZCVOhebT","popularity":15.0}
{"_id":{"$oid":"5d897bc981ba0d56dff18fd9"},"artist":"Wade Walton","spotifyID":"75cBND8wmzB7MpI43i0ZiC","popularity":0.0}
{"_id":{"$oid":"5d897bc981ba0d56dff18fda"},"artist":"Willie Brown","spotifyID":"6zxIBQ4sNvQCSkciayJxaS","popularity":20.0}
{"_id":{"$oid":"5d897bc981ba0d56dff18fdb"},"artist":"Eddie Boyd","spotifyID":"6tlPbmYME3fjRkSBb3pjoB","popularity":27.0}
{"_id":{"$oid":"5d897bc981ba0d56dff18fdc"},"artist":"Frank Stokes","spotifyID":"3dahhupQzKVXptEwFBsodc","popularity":28.0}
{"_id":{"$oid":"5d897bc981ba0d56dff18fdd"},"artist":"Nate Dogg","spotifyID":"1Oa0bMld0A3u5OTYfMzp5h","popularity":77.0}
{"_id":{"$oid":"5d897bc981ba0d56dff18fde"},"artist":"Clayton Love","spotifyID":"2qZyf9lZcfR4DgRIsyB4t0","popularity":0.0}
{"_id":{"$oid":"5d897bc981ba0d56dff18fdf"},"artist":"Brother John Sellers","spotifyID":"4pilDuC439vsXN7aRzF7mp","popularity":6.0}
{"_id":{"$oid":"5d897bc981ba0d56dff18fe0"},"artist":"Marshall Drew","spotifyID":"6Jr1FrehwBalXe10QJujqe","popularity":0.0}
{"_id":{"$oid":"5d897bc981ba0d56dff18fe1"},"artist":"Blind Mississippi Morris","spotifyID":"5HeW7xcRB2utN0Fo5rbhAz","popularity":6.0}
{"_id":{"$oid":"5d897bc981ba0d56dff18fe2"},"artist":"Robert Walker","spotifyID":"0zsgZJZvwAA2V15Jc5yOLB","popularity":4.0}
{"_id":{"$oid":"5d897bc981ba0d56dff18fe3"},"artist":"Super Chikan","spotifyID":"4OVYHrWUNZs9IB5aeWHsUE","popularity":10.0}
{"_id":{"$oid":"5d897bc981ba0d56dff18fe4"},"artist":"Ike Turner","spotifyID":"1ZikppG9dPedbIgMfnfx8k","popularity":57.0}
{"_id":{"$oid":"5d897bc981ba0d56dff18fe5"},"artist":"Mack Rice","spotifyID":"5ZAdhQ0HJFv85oFNgrkCpi","popularity":13.0}
{"_id":{"$oid":"5d897bc981ba0d56dff18fe6"},"artist":"Muddy Waters","spotifyID":"4y6J8jwRAwO4dssiSmN91R","popularity":58.0}
{"_id":{"$oid":"5d897bc981ba0d56dff18fe7"},"artist":"Junior Parker","spotifyID":"0NyzfcGDZZ6GM25EBG9BYK","popularity":55.0}
