{"_id":{"$oid":"5d8cfc0fff66aa68f48f0a8b"},"artist":"Mat Devine","spotifyID":"1NBMOzDkQrdmP9sq6RiTua","popularity":11.0}
{"_id":{"$oid":"5d8cfc0fff66aa68f48f0a8c"},"artist":"Paul Avgerinos","spotifyID":"06iIl4IfaJnZ19GqOovQAn","popularity":34.0}
{"_id":{"$oid":"5d8cfc0fff66aa68f48f0a8d"},"artist":"Joan As Police Woman","spotifyID":"6PBv8t9YTLggA9ZMwpeoqj","popularity":44.0}
{"_id":{"$oid":"5d8cfc0fff66aa68f48f0a8e"},"artist":"P.J. Pacifico","spotifyID":"0ng9cvYy8y2xAiYPefoyfy","popularity":11.0}
{"_id":{"$oid":"5d8cfc0fff66aa68f48f0a8f"},"artist":"Jim Wolf","spotifyID":"4a3NWlfXrBdbQ4NlD6h1UP","popularity":4.0}
{"_id":{"$oid":"5d8cfc0fff66aa68f48f0a90"},"artist":"Jason Goldman","spotifyID":"438G5f1lbFqRxEVYjoIN38","popularity":0.0}
{"_id":{"$oid":"5d8cfc0fff66aa68f48f0a91"},"artist":"Christopher Schreiner","spotifyID":"4IWPqEPTe57X6U44jixig8","popularity":0.0}
{"_id":{"$oid":"5d8cfc0fff66aa68f48f0a92"},"artist":"Farrad","spotifyID":"11I21ryoTqns4Uj2GP0Lny","popularity":0.0}
{"_id":{"$oid":"5d8cfc0fff66aa68f48f0a93"},"artist":"Dave Brubeck","spotifyID":"4iRZAbYvBqnxrbs6K25aJ7","popularity":57.0}
{"_id":{"$oid":"5d8cfc0fff66aa68f48f0a94"},"artist":"Horace Silver","spotifyID":"5ZATfKurLqflrBhv2FLht5","popularity":49.0}
{"_id":{"$oid":"5d8cfc0fff66aa68f48f0a95"},"artist":"Michael DeMaria","spotifyID":"4J85f6hTod2Mz1JIWnfgRz","popularity":30.0}
{"_id":{"$oid":"5d8cfc0fff66aa68f48f0a96"},"artist":"Andy Rinehart","spotifyID":"3DUU1LnsSoZKCp6I5oOBuD","popularity":0.0}
{"_id":{"$oid":"5d8cfc0fff66aa68f48f0a97"},"artist":"Vince Mendoza","spotifyID":"4E9rsN1uXPIM0zc9CwVBSt","popularity":27.0}
{"_id":{"$oid":"5d8cfc0fff66aa68f48f0a98"},"artist":"Chris Webby","spotifyID":"3IstlZaHyUP9SONpulb4SM","popularity":66.0}
{"_id":{"$oid":"5d8cfc0fff66aa68f48f0a99"},"artist":"John Simon","spotifyID":"1TQI0TIso5ddKG9pbhM4ZE","popularity":0.0}
{"_id":{"$oid":"5d8cfc0fff66aa68f48f0a9a"},"artist":"Tom Salta","spotifyID":"0KFl3wbs0hvoKlKDPcXODj","popularity":47.0}
{"_id":{"$oid":"5d8cfc0fff66aa68f48f0a9b"},"artist":"Eliot Lewis","spotifyID":"0JXAHFq6so4kLGkMmUyD7X","popularity":0.0}
{"_id":{"$oid":"5d8cfc0fff66aa68f48f0a9c"},"artist":"Omar Wilson","spotifyID":"3mTCamd3Mo72bMTw8XzLTP","popularity":16.0}
{"_id":{"$oid":"5d8cfc0fff66aa68f48f0a9d"},"artist":"Adam Nussbaum","spotifyID":"1ymZAHNSJ5rvzjW01iwQRi","popularity":19.0}
